flask_flashy/__init__.py
flask_flashy-0.2.2.dist-info/licenses/LICENSE
flask_flashy-0.2.2.dist-info/METADATA
flask_flashy-0.2.2.dist-info/WHEEL
flask_flashy-0.2.2.dist-info/top_level.txt
flask_flashy-0.2.2.dist-info/RECORD
