Metadata-Version: 2.4
Name: flask-flashy
Version: 0.2.2
Summary: Custom flash system allowing custom keyword arguments for Flask.
Home-page: https://github.com/UsernameIsInUse/flask-flashy
Author: Alex Chichester
Author-email: alexcchichester@gmail.com
License: BSD 3-clause
Classifier: Development Status :: 3 - Alpha
Classifier: Intended Audience :: Developers
Classifier: Natural Language :: English
Classifier: Programming Language :: Python :: 3
Classifier: Programming Language :: Python :: 3.12
License-File: LICENSE
Requires-Dist: Flask
Dynamic: author
Dynamic: author-email
Dynamic: classifier
Dynamic: description
Dynamic: description-content-type
Dynamic: home-page
Dynamic: license
Dynamic: license-file
Dynamic: requires-dist
Dynamic: summary
